datamodels/__init__.py
datamodels/field.py
datamodels/model.py
datamodels/sql.py
datamodels/util.py
datamodels/validators.py
datamodels/xml.py
datamodels/tests/__init__.py
datamodels-0.8.2.dist-info/LICENSE
datamodels-0.8.2.dist-info/METADATA
datamodels-0.8.2.dist-info/WHEEL
datamodels-0.8.2.dist-info/top_level.txt
datamodels-0.8.2.dist-info/RECORD
