Metadata-Version: 2.1
Name: datamodels
Version: 0.8.2
Summary: Models for Pythonistas
Home-page: https://github.com/blackearth/datamodels
Author: Sean Harrison
Author-email: sah@bookgenesis.com
License: MPL 2.0
Platform: UNKNOWN
Classifier: Development Status :: 3 - Alpha
Classifier: Intended Audience :: Developers
Classifier: License :: OSI Approved :: Mozilla Public License 2.0 (MPL 2.0)
Classifier: Programming Language :: Python :: 3.7
Classifier: Programming Language :: Python :: 3.8
Provides-Extra: dev
Requires-Dist: twine ; extra == 'dev'
Provides-Extra: test
